AUTHORS
LICENSE
MANIFEST.in
README.rst
setup.cfg
setup.py
libv8/Makefile
libv8/build/README.txt
libv8/build/all.gyp
libv8/build/android.gypi
libv8/build/features.gypi
libv8/build/gyp_v8
libv8/build/gyp_v8.py
libv8/build/shim_headers.gypi
libv8/build/standalone.gypi
libv8/build/standalone.gypi.bak
libv8/build/toolchain.gypi
libv8/build/gyp/.gitignore
libv8/build/gyp/AUTHORS
libv8/build/gyp/DEPS
libv8/build/gyp/LICENSE
libv8/build/gyp/OWNERS
libv8/build/gyp/PRESUBMIT.py
libv8/build/gyp/codereview.settings
libv8/build/gyp/gyp
libv8/build/gyp/gyp.bat
libv8/build/gyp/gyp_dummy.c
libv8/build/gyp/gyp_main.py
libv8/build/gyp/gyptest.py
libv8/build/gyp/pylintrc
libv8/build/gyp/setup.py
libv8/build/gyp/data/win/large-pdb-shim.cc
libv8/build/gyp/pylib/gyp/MSVSNew.py
libv8/build/gyp/pylib/gyp/MSVSProject.py
libv8/build/gyp/pylib/gyp/MSVSSettings.py
libv8/build/gyp/pylib/gyp/MSVSSettings_test.py
libv8/build/gyp/pylib/gyp/MSVSToolFile.py
libv8/build/gyp/pylib/gyp/MSVSUserFile.py
libv8/build/gyp/pylib/gyp/MSVSUtil.py
libv8/build/gyp/pylib/gyp/MSVSVersion.py
libv8/build/gyp/pylib/gyp/__init__.py
libv8/build/gyp/pylib/gyp/__init__.pyc
libv8/build/gyp/pylib/gyp/common.py
libv8/build/gyp/pylib/gyp/common.pyc
libv8/build/gyp/pylib/gyp/common_test.py
libv8/build/gyp/pylib/gyp/easy_xml.py
libv8/build/gyp/pylib/gyp/easy_xml_test.py
libv8/build/gyp/pylib/gyp/flock_tool.py
libv8/build/gyp/pylib/gyp/input.py
libv8/build/gyp/pylib/gyp/input.pyc
libv8/build/gyp/pylib/gyp/input_test.py
libv8/build/gyp/pylib/gyp/mac_tool.py
libv8/build/gyp/pylib/gyp/msvs_emulation.py
libv8/build/gyp/pylib/gyp/ninja_syntax.py
libv8/build/gyp/pylib/gyp/ordered_dict.py
libv8/build/gyp/pylib/gyp/win_tool.py
libv8/build/gyp/pylib/gyp/xcode_emulation.py
libv8/build/gyp/pylib/gyp/xcode_emulation.pyc
libv8/build/gyp/pylib/gyp/xcodeproj_file.py
libv8/build/gyp/pylib/gyp/xml_fix.py
libv8/build/gyp/pylib/gyp/generator/__init__.py
libv8/build/gyp/pylib/gyp/generator/__init__.pyc
v8.egg-info/PKG-INFO
v8.egg-info/SOURCES.txt
v8.egg-info/dependency_links.txt
v8.egg-info/top_level.txt