Metadata-Version: 1.1
Name: v8
Version: 0.1.5
Summary: Python Wrapper for Google V8 Engine
Home-page: http://github.com/damoti/python-v8
Author: Lex Berezhny
Author-email: lex@damoti.com
License: Apache Software License
Keywords: js javascript v8
Platform: linux
Platform: osx
Platform: cygwin
Platform: win32
Classifier: Programming Language :: C++
Classifier: Programming Language :: Python
Classifier: Programming Language :: Python :: 3
Classifier: Development Status :: 4 - Beta
Classifier: Environment :: Plugins
Classifier: Environment :: Console
Classifier: Intended Audience :: Developers
Classifier: Intended Audience :: System Administrators
Classifier: License :: OSI Approved :: Apache Software License
Classifier: Operating System :: OS Independent
Classifier: Topic :: Internet :: WWW/HTTP
Classifier: Topic :: Software Development
Classifier: Topic :: Software Development :: Libraries :: Python Modules
Classifier: Topic :: Utilities
